{"add":{"path":"part-00001-bd47c2ca-fe32-4f54-af12-e450a231cd42-c000.snappy.parquet","partitionValues":{},"size":3175,"modificationTime":1760917451859,"dataChange":true,"stats":"{\"numRecords\":1,\"minValues\":{\"date\":\"2025-10-15\",\"id\":1986,\"amount\":3199.0,\"category_id\":5,\"user_id\":15,\"account_id\":2,\"description\":\"Compra de roupas\",\"type\":\"saída\"},\"maxValues\":{\"description\":\"Compra de roupas\",\"user_id\":15,\"id\":1986,\"type\":\"saída\",\"account_id\":2,\"amount\":3199.0,\"date\":\"2025-10-15\",\"category_id\":5},\"nullCount\":{\"description\":0,\"id\":0,\"amount\":0,\"category_id\":0,\"type\":0,\"date\":0,\"account_id\":0,\"user_id\":0}}","tags":null,"deletionVector":null,"baseRowId":null,"defaultRowCommitVersion":null,"clusteringProvider":null}}
{"commitInfo":{"timestamp":1760917451859,"operation":"WRITE","operationParameters":{"mode":"Append"},"operationMetrics":{"execution_time_ms":0,"num_added_files":1,"num_added_rows":1,"num_partitions":0,"num_removed_files":0},"clientVersion":"delta-rs.0.20.1"}}