{"add":{"path":"part-00001-831e9cfe-5182-49fd-9142-3f6c29eb273c-c000.snappy.parquet","partitionValues":{},"size":3138,"modificationTime":1760917427488,"dataChange":true,"stats":"{\"numRecords\":1,\"minValues\":{\"amount\":914.54,\"type\":\"saída\",\"category_id\":6,\"date\":\"2025-03-07\",\"account_id\":1,\"id\":1239,\"user_id\":10,\"description\":\"Curso online\"},\"maxValues\":{\"category_id\":6,\"id\":1239,\"description\":\"Curso online\",\"account_id\":1,\"amount\":914.54,\"date\":\"2025-03-07\",\"user_id\":10,\"type\":\"saída\"},\"nullCount\":{\"amount\":0,\"id\":0,\"description\":0,\"date\":0,\"user_id\":0,\"account_id\":0,\"category_id\":0,\"type\":0}}","tags":null,"deletionVector":null,"baseRowId":null,"defaultRowCommitVersion":null,"clusteringProvider":null}}
{"commitInfo":{"timestamp":1760917427488,"operation":"WRITE","operationParameters":{"mode":"Append"},"clientVersion":"delta-rs.0.20.1","operationMetrics":{"execution_time_ms":0,"num_added_files":1,"num_added_rows":1,"num_partitions":0,"num_removed_files":0}}}