{"add":{"path":"part-00001-064ddc2b-4742-4a31-bf7f-dfcb6fea8907-c000.snappy.parquet","partitionValues":{},"size":3220,"modificationTime":1760917452340,"dataChange":true,"stats":"{\"numRecords\":1,\"minValues\":{\"category_id\":5,\"amount\":2947.24,\"user_id\":3,\"date\":\"2025-07-03\",\"description\":\"Pagamento de aluguel\",\"type\":\"entrada\",\"account_id\":4,\"id\":1995},\"maxValues\":{\"amount\":2947.24,\"id\":1995,\"category_id\":5,\"date\":\"2025-07-03\",\"description\":\"Pagamento de aluguel\",\"account_id\":4,\"type\":\"entrada\",\"user_id\":3},\"nullCount\":{\"account_id\":0,\"amount\":0,\"date\":0,\"user_id\":0,\"id\":0,\"category_id\":0,\"description\":0,\"type\":0}}","tags":null,"deletionVector":null,"baseRowId":null,"defaultRowCommitVersion":null,"clusteringProvider":null}}
{"commitInfo":{"timestamp":1760917452340,"operation":"WRITE","operationParameters":{"mode":"Append"},"clientVersion":"delta-rs.0.20.1","operationMetrics":{"execution_time_ms":0,"num_added_files":1,"num_added_rows":1,"num_partitions":0,"num_removed_files":0}}}