{"add":{"path":"part-00001-8c736c11-5c1f-4e59-be05-c00c659fd651-c000.snappy.parquet","partitionValues":{},"size":3147,"modificationTime":1760917436718,"dataChange":true,"stats":"{\"numRecords\":1,\"minValues\":{\"user_id\":12,\"type\":\"entrada\",\"account_id\":4,\"id\":1613,\"amount\":2576.04,\"category_id\":3,\"description\":\"Curso online\",\"date\":\"2025-04-12\"},\"maxValues\":{\"date\":\"2025-04-12\",\"account_id\":4,\"id\":1613,\"user_id\":12,\"type\":\"entrada\",\"amount\":2576.04,\"category_id\":3,\"description\":\"Curso online\"},\"nullCount\":{\"amount\":0,\"description\":0,\"category_id\":0,\"type\":0,\"user_id\":0,\"id\":0,\"date\":0,\"account_id\":0}}","tags":null,"deletionVector":null,"baseRowId":null,"defaultRowCommitVersion":null,"clusteringProvider":null}}
{"commitInfo":{"timestamp":1760917436718,"operation":"WRITE","operationParameters":{"mode":"Append"},"clientVersion":"delta-rs.0.20.1","operationMetrics":{"execution_time_ms":0,"num_added_files":1,"num_added_rows":1,"num_partitions":0,"num_removed_files":0}}}