{"add":{"path":"part-00001-5ae1b2ad-9113-4f24-b358-1a8e62136e39-c000.snappy.parquet","partitionValues":{},"size":3229,"modificationTime":1760917425404,"dataChange":true,"stats":"{\"numRecords\":1,\"minValues\":{\"description\":\"Compra no supermercado\",\"type\":\"saída\",\"date\":\"2025-01-03\",\"amount\":1680.14,\"category_id\":1,\"account_id\":6,\"id\":1077,\"user_id\":13},\"maxValues\":{\"id\":1077,\"date\":\"2025-01-03\",\"user_id\":13,\"category_id\":1,\"type\":\"saída\",\"account_id\":6,\"description\":\"Compra no supermercado\",\"amount\":1680.14},\"nullCount\":{\"type\":0,\"amount\":0,\"account_id\":0,\"category_id\":0,\"user_id\":0,\"date\":0,\"id\":0,\"description\":0}}","tags":null,"deletionVector":null,"baseRowId":null,"defaultRowCommitVersion":null,"clusteringProvider":null}}
{"commitInfo":{"timestamp":1760917425404,"operation":"WRITE","operationParameters":{"mode":"Append"},"clientVersion":"delta-rs.0.20.1","operationMetrics":{"execution_time_ms":0,"num_added_files":1,"num_added_rows":1,"num_partitions":0,"num_removed_files":0}}}