{"add":{"path":"part-00001-8b97da0f-848e-41f5-b321-013a45eb40c5-c000.snappy.parquet","partitionValues":{},"size":3147,"modificationTime":1760917429812,"dataChange":true,"stats":"{\"numRecords\":1,\"minValues\":{\"account_id\":9,\"type\":\"entrada\",\"date\":\"2025-08-28\",\"amount\":802.11,\"id\":1362,\"description\":\"Curso online\",\"category_id\":4,\"user_id\":6},\"maxValues\":{\"category_id\":4,\"user_id\":6,\"description\":\"Curso online\",\"id\":1362,\"type\":\"entrada\",\"date\":\"2025-08-28\",\"account_id\":9,\"amount\":802.11},\"nullCount\":{\"user_id\":0,\"date\":0,\"type\":0,\"description\":0,\"id\":0,\"account_id\":0,\"category_id\":0,\"amount\":0}}","tags":null,"deletionVector":null,"baseRowId":null,"defaultRowCommitVersion":null,"clusteringProvider":null}}
{"commitInfo":{"timestamp":1760917429812,"operation":"WRITE","operationParameters":{"mode":"Append"},"clientVersion":"delta-rs.0.20.1","operationMetrics":{"execution_time_ms":0,"num_added_files":1,"num_added_rows":1,"num_partitions":0,"num_removed_files":0}}}