{"add":{"path":"part-00001-2be0d1e9-08f4-489a-9c9d-6ede701e0fb4-c000.snappy.parquet","partitionValues":{},"size":3238,"modificationTime":1760917451662,"dataChange":true,"stats":"{\"numRecords\":1,\"minValues\":{\"category_id\":6,\"user_id\":6,\"id\":1982,\"description\":\"Compra no supermercado\",\"type\":\"entrada\",\"amount\":3624.21,\"account_id\":4,\"date\":\"2024-10-28\"},\"maxValues\":{\"account_id\":4,\"date\":\"2024-10-28\",\"id\":1982,\"amount\":3624.21,\"category_id\":6,\"description\":\"Compra no supermercado\",\"type\":\"entrada\",\"user_id\":6},\"nullCount\":{\"account_id\":0,\"amount\":0,\"description\":0,\"category_id\":0,\"date\":0,\"id\":0,\"user_id\":0,\"type\":0}}","tags":null,"deletionVector":null,"baseRowId":null,"defaultRowCommitVersion":null,"clusteringProvider":null}}
{"commitInfo":{"timestamp":1760917451662,"operation":"WRITE","operationParameters":{"mode":"Append"},"clientVersion":"delta-rs.0.20.1","operationMetrics":{"execution_time_ms":0,"num_added_files":1,"num_added_rows":1,"num_partitions":0,"num_removed_files":0}}}