{"add":{"path":"part-00001-7588e264-f393-470e-9b41-85001a29f55d-c000.snappy.parquet","partitionValues":{},"size":3147,"modificationTime":1760917433639,"dataChange":true,"stats":"{\"numRecords\":1,\"minValues\":{\"category_id\":6,\"description\":\"Curso online\",\"date\":\"2025-05-08\",\"account_id\":2,\"amount\":3669.81,\"id\":1513,\"user_id\":9,\"type\":\"entrada\"},\"maxValues\":{\"type\":\"entrada\",\"amount\":3669.81,\"id\":1513,\"date\":\"2025-05-08\",\"account_id\":2,\"category_id\":6,\"description\":\"Curso online\",\"user_id\":9},\"nullCount\":{\"id\":0,\"category_id\":0,\"user_id\":0,\"type\":0,\"description\":0,\"date\":0,\"account_id\":0,\"amount\":0}}","tags":null,"deletionVector":null,"baseRowId":null,"defaultRowCommitVersion":null,"clusteringProvider":null}}
{"commitInfo":{"timestamp":1760917433639,"operation":"WRITE","operationParameters":{"mode":"Append"},"clientVersion":"delta-rs.0.20.1","operationMetrics":{"execution_time_ms":0,"num_added_files":1,"num_added_rows":1,"num_partitions":0,"num_removed_files":0}}}