{"add":{"path":"part-00001-85821042-173b-4d1b-95d6-735e9f297dd7-c000.snappy.parquet","partitionValues":{},"size":3238,"modificationTime":1760917439875,"dataChange":true,"stats":"{\"numRecords\":1,\"minValues\":{\"type\":\"saída\",\"description\":\"Assinatura de streaming\",\"category_id\":3,\"date\":\"2025-04-10\",\"amount\":466.72,\"id\":1703,\"account_id\":5,\"user_id\":12},\"maxValues\":{\"amount\":466.72,\"date\":\"2025-04-10\",\"account_id\":5,\"id\":1703,\"description\":\"Assinatura de streaming\",\"type\":\"saída\",\"category_id\":3,\"user_id\":12},\"nullCount\":{\"account_id\":0,\"user_id\":0,\"id\":0,\"description\":0,\"category_id\":0,\"type\":0,\"amount\":0,\"date\":0}}","tags":null,"deletionVector":null,"baseRowId":null,"defaultRowCommitVersion":null,"clusteringProvider":null}}
{"commitInfo":{"timestamp":1760917439875,"operation":"WRITE","operationParameters":{"mode":"Append"},"clientVersion":"delta-rs.0.20.1","operationMetrics":{"execution_time_ms":0,"num_added_files":1,"num_added_rows":1,"num_partitions":0,"num_removed_files":0}}}