{"add":{"path":"part-00001-c76dc50c-160d-4c02-9637-3eac8ddb80ad-c000.snappy.parquet","partitionValues":{},"size":3184,"modificationTime":1760917431334,"dataChange":true,"stats":"{\"numRecords\":1,\"minValues\":{\"user_id\":18,\"description\":\"Consulta médica\",\"account_id\":6,\"type\":\"entrada\",\"category_id\":5,\"id\":1427,\"date\":\"2025-04-24\",\"amount\":890.47},\"maxValues\":{\"date\":\"2025-04-24\",\"user_id\":18,\"amount\":890.47,\"type\":\"entrada\",\"description\":\"Consulta médica\",\"category_id\":5,\"account_id\":6,\"id\":1427},\"nullCount\":{\"date\":0,\"id\":0,\"account_id\":0,\"description\":0,\"category_id\":0,\"user_id\":0,\"type\":0,\"amount\":0}}","tags":null,"deletionVector":null,"baseRowId":null,"defaultRowCommitVersion":null,"clusteringProvider":null}}
{"commitInfo":{"timestamp":1760917431334,"operation":"WRITE","operationParameters":{"mode":"Append"},"clientVersion":"delta-rs.0.20.1","operationMetrics":{"execution_time_ms":0,"num_added_files":1,"num_added_rows":1,"num_partitions":0,"num_removed_files":0}}}